{
  "name": "multifile-calendar-window",
  "suite": "v2-multifile",
  "bug_shape": "calendar constants and inclusive window drift",
  "goal": "Repair weekend constants and inclusive booking-window logic together.",
  "test_command": "pytest",
  "expected_changed_source_files": ["calendar_rules/constants.py", "calendar_rules/window.py"],
  "allowed_changed_files": ["calendar_rules/constants.py", "calendar_rules/window.py"],
  "minimum_changed_files": 2,
  "expected_validation_commands": ["pytest tests/test_calendar_rules.py", "pytest"],
  "flagship": true
}
